postfiat_wallet/__init__.py
postfiat_wallet/__main__.py
postfiat_wallet/cli.py
postfiat_wallet/config.py
postfiat_wallet/constants.py
postfiat_wallet/server/__init__.py
postfiat_wallet/server/api.py
postfiat_wallet/server/app.py
postfiat_wallet/server/websocket.py
postfiat_wallet/services/__init__.py
postfiat_wallet/services/blockchain.py
postfiat_wallet/services/odv_service.py
postfiat_wallet/services/rpc_client_wrapper.py
postfiat_wallet/services/storage.py
postfiat_wallet/services/task_storage.py
postfiat_wallet/services/transaction.py
postfiat_wallet/static/404.html
postfiat_wallet/static/favicon.ico
postfiat_wallet/static/file.svg
postfiat_wallet/static/globe.svg
postfiat_wallet/static/index.html
postfiat_wallet/static/index.txt
postfiat_wallet/static/next.svg
postfiat_wallet/static/vercel.svg
postfiat_wallet/static/window.svg
postfiat_wallet/static/_next/static/2025-03-14T05-38-12-736Z/_buildManifest.js
postfiat_wallet/static/_next/static/2025-03-14T05-38-12-736Z/_ssgManifest.js
postfiat_wallet/static/_next/static/chunks/4bd1b696-2cc406ff1fc3879e.js
postfiat_wallet/static/_next/static/chunks/517-f1a4ec0788abfb4d.js
postfiat_wallet/static/_next/static/chunks/529.eba8768e25ee24c7.js
postfiat_wallet/static/_next/static/chunks/framework-6b27c2b7aa38af2d.js
postfiat_wallet/static/_next/static/chunks/main-abc0756c0d8cbf26.js
postfiat_wallet/static/_next/static/chunks/main-app-d370bebe3146465c.js
postfiat_wallet/static/_next/static/chunks/polyfills-42372ed130431b0a.js
postfiat_wallet/static/_next/static/chunks/webpack-7db82840f8a4ea51.js
postfiat_wallet/static/_next/static/chunks/app/layout-445e48604242e2b4.js
postfiat_wallet/static/_next/static/chunks/app/page-30762848d475659c.js
postfiat_wallet/static/_next/static/chunks/app/_not-found/page-740d5d595c140654.js
postfiat_wallet/static/_next/static/chunks/pages/_app-d23763e3e6c904ff.js
postfiat_wallet/static/_next/static/chunks/pages/_error-9b7125ad1a1e68fa.js
postfiat_wallet-0.1.5.dist-info/METADATA
postfiat_wallet-0.1.5.dist-info/WHEEL
postfiat_wallet-0.1.5.dist-info/entry_points.txt
postfiat_wallet-0.1.5.dist-info/licenses/LICENSE
postfiat_wallet-0.1.5.dist-info/RECORD
