Metadata-Version: 2.3
Name: postfiat-wallet
Version: 0.1.5
Summary: Local Wallet for the Post Fiat Network
License: MPL-2.0
Requires-Python: >=3.12
Requires-Dist: boto3==1.36.26
Requires-Dist: click==8.1.8
Requires-Dist: cryptography==44.0.2
Requires-Dist: dynaconf==3.2.10
Requires-Dist: fastapi==0.115.11
Requires-Dist: packaging==24.2
Requires-Dist: postfiat-sdk==0.1.1a202503131857
Requires-Dist: requests==2.32.3
Requires-Dist: uvicorn==0.34.0
Requires-Dist: websockets==13.1
Requires-Dist: xrpl-py==4.0.0
Provides-Extra: dev
Requires-Dist: black; extra == 'dev'
Requires-Dist: hatch; extra == 'dev'
Requires-Dist: isort; extra == 'dev'
Requires-Dist: mypy; extra == 'dev'
Requires-Dist: pytest; extra == 'dev'
Requires-Dist: pytest-asyncio; extra == 'dev'
